lintrunner_adapters/__init__.py
lintrunner_adapters/__main__.py
lintrunner_adapters/_common/lintrunner_common.py
lintrunner_adapters/adapters/add_trailing_comma_linter.py
lintrunner_adapters/adapters/bandit_linter.py
lintrunner_adapters/adapters/black_isort_linter.py
lintrunner_adapters/adapters/black_linter.py
lintrunner_adapters/adapters/clangformat_linter.py
lintrunner_adapters/adapters/clippy_linter.py
lintrunner_adapters/adapters/cmake_format_linter.py
lintrunner_adapters/adapters/cmake_linter.py
lintrunner_adapters/adapters/django_upgrade_linter.py
lintrunner_adapters/adapters/docformatter_linter.py
lintrunner_adapters/adapters/editorconfig_checker_linter.py
lintrunner_adapters/adapters/exec_linter.py
lintrunner_adapters/adapters/flake8_linter.py
lintrunner_adapters/adapters/grep_linter.py
lintrunner_adapters/adapters/isort_linter.py
lintrunner_adapters/adapters/mypy_linter.py
lintrunner_adapters/adapters/newlines_linter.py
lintrunner_adapters/adapters/pip_init.py
lintrunner_adapters/adapters/pylint_linter.py
lintrunner_adapters/adapters/pyupgrade_linter.py
lintrunner_adapters/adapters/refurb_linter.py
lintrunner_adapters/adapters/requirements_txt_linter.py
lintrunner_adapters/adapters/ruff_fix_linter.py
lintrunner_adapters/adapters/ruff_format_linter.py
lintrunner_adapters/adapters/ruff_linter.py
lintrunner_adapters/adapters/rustfmt_linter.py
lintrunner_adapters/adapters/shellcheck_linter.py
lintrunner_adapters/adapters/toml_sort_linter.py
lintrunner_adapters/adapters/ufmt_linter.py
lintrunner_adapters/tools/convert_to_sarif.py
lintrunner_adapters/tools/convert_to_sarif_test.py
lintrunner_adapters-0.13.0.dist-info/licenses/LICENSE
lintrunner_adapters-0.13.0.dist-info/METADATA
lintrunner_adapters-0.13.0.dist-info/WHEEL
lintrunner_adapters-0.13.0.dist-info/entry_points.txt
lintrunner_adapters-0.13.0.dist-info/top_level.txt
lintrunner_adapters-0.13.0.dist-info/RECORD
