Metadata-Version: 2.4
Name: lintrunner-adapters
Version: 0.13.0
Summary: Adapters and tools for lintrunner
Author-email: Justin Chu <justinchu@microsoft.com>
License-Expression: MIT
Project-URL: Repository, https://github.com/justinchuby/lintrunner-adapters
Keywords: lintrunner,lint,cli,sarif,linting,ci,linter,flake8,clippy,ruff,rustfmt,github-code-scanning
Classifier: Topic :: Software Development :: Testing
Classifier: Topic :: Software Development :: Quality Assurance
Requires-Python: >=3.9
License-File: LICENSE
Requires-Dist: click>=8.1.3
Provides-Extra: dev
Requires-Dist: lintrunner>=0.10.0; extra == "dev"
Requires-Dist: pytest>=7.2.0; extra == "dev"
Requires-Dist: types-pyyaml>=6.0.12.2; extra == "dev"
Dynamic: license-file
